ioload.py
ioload-1.0.0.dist-info/METADATA
ioload-1.0.0.dist-info/WHEEL
ioload-1.0.0.dist-info/entry_points.txt
ioload-1.0.0.dist-info/top_level.txt
ioload-1.0.0.dist-info/RECORD
