Metadata-Version: 2.4
Name: ioload
Version: 1.0.0
Summary: A wrapper for iostat that displays I/O statistics in a real-time chart format
Author: ioload contributors
Project-URL: Homepage, https://github.com/guntanis/ioload
Project-URL: Documentation, https://github.com/guntanis/ioload#readme
Project-URL: Repository, https://github.com/guntanis/ioload
Project-URL: Issues, https://github.com/guntanis/ioload/issues
Keywords: iostat,monitoring,io,statistics,terminal,curses,chart
Classifier: Development Status :: 4 - Beta
Classifier: Intended Audience :: System Administrators
Classifier: Intended Audience :: Developers
Classifier: Topic :: System :: Monitoring
Classifier: Topic :: System :: Systems Administration
Classifier: License :: OSI Approved :: MIT License
Classifier: Programming Language :: Python :: 3
Classifier: Programming Language :: Python :: 3.6
Classifier: Programming Language :: Python :: 3.7
Classifier: Programming Language :: Python :: 3.8
Classifier: Programming Language :: Python :: 3.9
Classifier: Programming Language :: Python :: 3.10
Classifier: Programming Language :: Python :: 3.11
Classifier: Programming Language :: Python :: 3.12
Classifier: Operating System :: POSIX :: Linux
Classifier: Operating System :: MacOS
Classifier: Operating System :: Unix
Classifier: Environment :: Console :: Curses
Requires-Python: >=3.6
Requires-Dist: asciichartpy>=1.5.3
Provides-Extra: dev
Requires-Dist: pytest>=7.0.0; extra == "dev"
Requires-Dist: black>=22.0.0; extra == "dev"
Requires-Dist: flake8>=5.0.0; extra == "dev"
Requires-Dist: mypy>=1.0.0; extra == "dev"
